gitpay/__init__.py
gitpay-0.1.0.dist-info/WHEEL
gitpay-0.1.0.dist-info/entry_points.txt
gitpay-0.1.0.dist-info/METADATA
gitpay-0.1.0.dist-info/RECORD
