Metadata-Version: 2.4
Name: gitpay
Version: 0.1.0
Summary: Pay anyone or anything on GitHub
Author: Mason Hall
Author-email: Mason Hall <masonhall@gmail.com>
License-Expression: MIT
Requires-Python: >=3.12
